mesoshttp/__init__.py
mesoshttp/acs.py
mesoshttp/client.py
mesoshttp/core.py
mesoshttp/exception.py
mesoshttp/offers.py
mesoshttp/update.py
mesoshttp-0.4.2.dist-info/LICENSE
mesoshttp-0.4.2.dist-info/METADATA
mesoshttp-0.4.2.dist-info/WHEEL
mesoshttp-0.4.2.dist-info/top_level.txt
mesoshttp-0.4.2.dist-info/RECORD
